9c46a97409a639359bbf__mypyc.cpython-311-darwin.so
quadint-stubs/quad.pyi
quadint-stubs/__init__.pyi
quadint-stubs/eisenstein.pyi
quadint-stubs/complex.pyi
quadint-0.0.9.dist-info/RECORD
quadint-0.0.9.dist-info/WHEEL
quadint-0.0.9.dist-info/top_level.txt
quadint-0.0.9.dist-info/METADATA
quadint-0.0.9.dist-info/licenses/LICENSE
quadint/eisenstein.cpython-311-darwin.so
quadint/complex.cpython-311-darwin.so
quadint/quad.cpython-311-darwin.so
quadint/__init__.cpython-311-darwin.so
