Metadata-Version: 2.4
Name: quadint
Version: 0.0.9
Summary: A quadint class, for using quadratic integers.
Author-email: Ryan Heard <ryanwheard@gmail.com>
License: MIT
Project-URL: Repository, https://github.com/rheard/quadint
Keywords: complex,math,eisenstein
Classifier: Programming Language :: Python :: 3
Classifier: Programming Language :: Python :: 3.8
Classifier: Programming Language :: Python :: 3.9
Classifier: Programming Language :: Python :: 3.10
Classifier: Programming Language :: Python :: 3.11
Classifier: Programming Language :: Python :: 3.12
Classifier: Programming Language :: Python :: 3.13
Classifier: Programming Language :: Python :: 3.14
Classifier: Programming Language :: Python :: Implementation :: CPython
Requires-Python: >=3.8
License-File: LICENSE
Dynamic: license
Dynamic: license-file
